docker_compose_parser/__init__.py
docker_compose_parser/file_models.py
docker_compose_parser/py.typed
docker_compose_parser-0.0.30.dist-info/METADATA
docker_compose_parser-0.0.30.dist-info/WHEEL
docker_compose_parser-0.0.30.dist-info/namespace_packages.txt
docker_compose_parser-0.0.30.dist-info/top_level.txt
docker_compose_parser-0.0.30.dist-info/RECORD
